interstice/__init__.py
interstice/demon.py
interstice/main.py
interstice/soldier.py
interstice-0.2.1.dist-info/LICENSE
interstice-0.2.1.dist-info/METADATA
interstice-0.2.1.dist-info/WHEEL
interstice-0.2.1.dist-info/top_level.txt
interstice-0.2.1.dist-info/RECORD
