Metadata-Version: 2.1
Name: interstice
Version: 0.2.1
Summary: A game of demons and soldiers on a 10x10 grid.
Author: Bananajump
Author-email: bananajump@bananajump.com
Classifier: Programming Language :: Python :: 3
Classifier: License :: OSI Approved :: MIT License
Classifier: Operating System :: OS Independent
Requires-Python: >=3.6
License-File: LICENSE
